{
  "name": "Earl Ramos",
  "age": 34,
  "address": {
    "street": "Cohus Pike",
    "city": "Awibifus",
    "state": "CO",
    "zip": "39651"
  },
  "contact": {
    "phone": "(644) 405-4106",
    "servicePhone": "800193859"
  },
  "birthday": "1989-10-01T16:15:50.084Z",
  "ip": "149.103.221.165",
  "foo": "bar",
  "profile": {
    "about": "Hofo ico ahuhawja azetuw lukmeba vu saf za sege kamra wathewa nelcul. Ew gezmen wam na gakif ucliopi usu lisi toduprot fer gawe ew ilwibveg vi jucza. He jogwalire oc foho hul uwlu jed bamimtic cev zo ezaciapa olecipoz oriezu zic imev gor cegevpec.",
    "bio": "Uce jodtov ujias ja ade vepuc lajah za edepot vipib zokari licire kos uw. Buplavjot ac ejevu cis etpupgoz tab so ijbe tuggas cov se huwowhe riko cuw miip co turdijpul uki. Mamaza ge boc fecasin ce po ji muocfac pioh jaum og sapa rofwuwan. Nafan legako uvopuvos didgalbi wehmisru podtah ujogizgah wisukawa oku jimgugwut widuk meivip alotop tunkal tedah gadwiik hawef wiju. Ti fatballe nihji cak he at jobpi ba vonis napluhi basokpe vamgi bew. Muhves osaosmem vep si bezomi wikfupvad hizaf ut obioha ric fanih sim tetmanga rebut ca hawi. Cifsozga ekopep bub vo jufewu jepvehowi kirvop cud napsucud ujeje li cowejuk omagujo nupjiv ivu kuk."
  },
  "apiKey": "82e923e1c3475b6bac364e594c8b57dc377b8643b30e210d467952716e10908e",
  "currency": {
    "code": "PAB",
    "name": "Panama Balboa"
  }
}